{
  "num_clusters": 28,
  "cluster_sizes": {
    "18": 100,
    "23": 100,
    "14": 313,
    "13": 167,
    "3": 365,
    "24": 64,
    "6": 231,
    "0": 352,
    "10": 473,
    "4": 627,
    "26": 189,
    "7": 308,
    "15": 194,
    "5": 380,
    "16": 177,
    "19": 156,
    "27": 206,
    "11": 195,
    "2": 626,
    "17": 131,
    "8": 221,
    "12": 201,
    "20": 189,
    "22": 299,
    "1": 217,
    "9": 202,
    "25": 203,
    "21": 124
  },
  "cluster_categories": {
    "18": {
      "Initializing": 100
    },
    "23": {
      "Initializing": 98,
      "Question Posing": 2
    },
    "14": {
      "Initializing": 179,
      "Adding Knowledge": 37,
      "Question Posing": 20,
      "Deduction": 58,
      "Example Testing": 16,
      "Metaphorical Thinking": 1,
      "Final Answer": 1,
      "Backtracking": 1
    },
    "13": {
      "Initializing": 124,
      "Question Posing": 28,
      "Backtracking": 5,
      "Adding Knowledge": 5,
      "Deduction": 4,
      "Example Testing": 1
    },
    "3": {
      "Adding Knowledge": 80,
      "Deduction": 131,
      "Uncertainty Estimation": 6,
      "Example Testing": 61,
      "Comparative Analysis": 5,
      "Final Answer": 18,
      "Question Posing": 23,
      "Metaphorical Thinking": 6,
      "Initializing": 21,
      "Backtracking": 2,
      "Summary": 12
    },
    "24": {
      "Initializing": 6,
      "Question Posing": 6,
      "Deduction": 17,
      "Adding Knowledge": 8,
      "Example Testing": 10,
      "Uncertainty Estimation": 5,
      "Backtracking": 6,
      "Final Answer": 6
    },
    "6": {
      "Uncertainty Estimation": 45,
      "Backtracking": 58,
      "Summary": 9,
      "Comparative Analysis": 1,
      "Question Posing": 21,
      "Deduction": 33,
      "Initializing": 20,
      "Adding Knowledge": 12,
      "Final Answer": 15,
      "Metaphorical Thinking": 2,
      "Example Testing": 15
    },
    "0": {
      "Initializing": 27,
      "Adding Knowledge": 22,
      "Deduction": 175,
      "Final Answer": 26,
      "Example Testing": 14,
      "Summary": 7,
      "Question Posing": 28,
      "Metaphorical Thinking": 3,
      "Uncertainty Estimation": 19,
      "Backtracking": 25,
      "Comparative Analysis": 6
    },
    "10": {
      "Initializing": 40,
      "Final Answer": 49,
      "Example Testing": 20,
      "Deduction": 252,
      "Question Posing": 38,
      "Metaphorical Thinking": 2,
      "Adding Knowledge": 26,
      "Uncertainty Estimation": 15,
      "Comparative Analysis": 9,
      "Backtracking": 17,
      "Summary": 5
    },
    "4": {
      "Initializing": 37,
      "Deduction": 295,
      "Summary": 14,
      "Adding Knowledge": 116,
      "Question Posing": 44,
      "Example Testing": 35,
      "Backtracking": 21,
      "Uncertainty Estimation": 17,
      "Final Answer": 40,
      "Comparative Analysis": 8
    },
    "26": {
      "Initializing": 11,
      "Deduction": 72,
      "Example Testing": 15,
      "Adding Knowledge": 16,
      "Final Answer": 18,
      "Question Posing": 15,
      "Uncertainty Estimation": 6,
      "Summary": 1,
      "Backtracking": 15,
      "Comparative Analysis": 18,
      "Metaphorical Thinking": 2
    },
    "7": {
      "Initializing": 26,
      "Example Testing": 33,
      "Question Posing": 11,
      "Deduction": 161,
      "Adding Knowledge": 27,
      "Uncertainty Estimation": 6,
      "Summary": 5,
      "Comparative Analysis": 6,
      "Final Answer": 17,
      "Backtracking": 14,
      "Metaphorical Thinking": 2
    },
    "15": {
      "Adding Knowledge": 29,
      "Initializing": 6,
      "Deduction": 73,
      "Question Posing": 27,
      "Backtracking": 41,
      "Uncertainty Estimation": 12,
      "Comparative Analysis": 3,
      "Example Testing": 3
    },
    "5": {
      "Deduction": 155,
      "Adding Knowledge": 85,
      "Question Posing": 28,
      "Example Testing": 32,
      "Final Answer": 17,
      "Metaphorical Thinking": 6,
      "Uncertainty Estimation": 8,
      "Backtracking": 16,
      "Summary": 6,
      "Initializing": 18,
      "Comparative Analysis": 9
    },
    "16": {
      "Initializing": 9,
      "Adding Knowledge": 5,
      "Deduction": 91,
      "Question Posing": 10,
      "Backtracking": 13,
      "Example Testing": 24,
      "Final Answer": 17,
      "Summary": 5,
      "Comparative Analysis": 2,
      "Uncertainty Estimation": 1
    },
    "19": {
      "Adding Knowledge": 11,
      "Initializing": 6,
      "Deduction": 65,
      "Backtracking": 10,
      "Example Testing": 28,
      "Question Posing": 14,
      "Comparative Analysis": 3,
      "Final Answer": 4,
      "Uncertainty Estimation": 14,
      "Summary": 1
    },
    "27": {
      "Question Posing": 30,
      "Deduction": 107,
      "Uncertainty Estimation": 3,
      "Adding Knowledge": 20,
      "Example Testing": 17,
      "Backtracking": 12,
      "Summary": 6,
      "Final Answer": 8,
      "Comparative Analysis": 3
    },
    "11": {
      "Initializing": 7,
      "Final Answer": 5,
      "Deduction": 89,
      "Example Testing": 29,
      "Backtracking": 22,
      "Question Posing": 19,
      "Uncertainty Estimation": 19,
      "Adding Knowledge": 2,
      "Summary": 2,
      "Comparative Analysis": 1
    },
    "2": {
      "Initializing": 53,
      "Deduction": 336,
      "Question Posing": 28,
      "Example Testing": 66,
      "Adding Knowledge": 41,
      "Final Answer": 29,
      "Backtracking": 33,
      "Summary": 15,
      "Comparative Analysis": 5,
      "Metaphorical Thinking": 7,
      "Uncertainty Estimation": 13
    },
    "17": {
      "Initializing": 2,
      "Adding Knowledge": 5,
      "Deduction": 51,
      "Example Testing": 3,
      "Uncertainty Estimation": 10,
      "Question Posing": 20,
      "Backtracking": 33,
      "Comparative Analysis": 5,
      "Summary": 2
    },
    "8": {
      "Summary": 6,
      "Deduction": 119,
      "Example Testing": 19,
      "Backtracking": 36,
      "Question Posing": 15,
      "Adding Knowledge": 7,
      "Uncertainty Estimation": 3,
      "Initializing": 10,
      "Final Answer": 6
    },
    "12": {
      "Deduction": 81,
      "Initializing": 25,
      "Adding Knowledge": 11,
      "Example Testing": 16,
      "Final Answer": 6,
      "Backtracking": 40,
      "Uncertainty Estimation": 9,
      "Question Posing": 13
    },
    "20": {
      "Initializing": 7,
      "Deduction": 113,
      "Question Posing": 18,
      "Adding Knowledge": 6,
      "Example Testing": 18,
      "Uncertainty Estimation": 4,
      "Backtracking": 18,
      "Final Answer": 3,
      "Comparative Analysis": 2
    },
    "22": {
      "Adding Knowledge": 21,
      "Initializing": 11,
      "Deduction": 140,
      "Example Testing": 27,
      "Uncertainty Estimation": 8,
      "Backtracking": 59,
      "Question Posing": 23,
      "Final Answer": 5,
      "Comparative Analysis": 3,
      "Summary": 2
    },
    "1": {
      "Deduction": 89,
      "Example Testing": 56,
      "Initializing": 15,
      "Adding Knowledge": 8,
      "Question Posing": 7,
      "Backtracking": 17,
      "Final Answer": 21,
      "Summary": 2,
      "Uncertainty Estimation": 1,
      "Comparative Analysis": 1
    },
    "9": {
      "Adding Knowledge": 4,
      "Deduction": 92,
      "Initializing": 22,
      "Backtracking": 37,
      "Question Posing": 22,
      "Uncertainty Estimation": 13,
      "Comparative Analysis": 5,
      "Example Testing": 5,
      "Final Answer": 2
    },
    "25": {
      "Deduction": 145,
      "Initializing": 10,
      "Question Posing": 14,
      "Example Testing": 11,
      "Backtracking": 7,
      "Adding Knowledge": 5,
      "Uncertainty Estimation": 6,
      "Metaphorical Thinking": 3,
      "Comparative Analysis": 1,
      "Final Answer": 1
    },
    "21": {
      "Adding Knowledge": 10,
      "Question Posing": 8,
      "Deduction": 55,
      "Initializing": 2,
      "Example Testing": 21,
      "Uncertainty Estimation": 7,
      "Backtracking": 5,
      "Metaphorical Thinking": 1,
      "Final Answer": 12,
      "Summary": 3
    }
  },
  "dominant_categories": {
    "18": {
      "category": "Initializing",
      "count": 100,
      "percentage": 100.0
    },
    "23": {
      "category": "Initializing",
      "count": 98,
      "percentage": 98.0
    },
    "14": {
      "category": "Initializing",
      "count": 179,
      "percentage": 57.18849840255591
    },
    "13": {
      "category": "Initializing",
      "count": 124,
      "percentage": 74.25149700598801
    },
    "3": {
      "category": "Deduction",
      "count": 131,
      "percentage": 35.89041095890411
    },
    "24": {
      "category": "Deduction",
      "count": 17,
      "percentage": 26.5625
    },
    "6": {
      "category": "Backtracking",
      "count": 58,
      "percentage": 25.108225108225106
    },
    "0": {
      "category": "Deduction",
      "count": 175,
      "percentage": 49.715909090909086
    },
    "10": {
      "category": "Deduction",
      "count": 252,
      "percentage": 53.276955602537
    },
    "4": {
      "category": "Deduction",
      "count": 295,
      "percentage": 47.04944178628389
    },
    "26": {
      "category": "Deduction",
      "count": 72,
      "percentage": 38.095238095238095
    },
    "7": {
      "category": "Deduction",
      "count": 161,
      "percentage": 52.27272727272727
    },
    "15": {
      "category": "Deduction",
      "count": 73,
      "percentage": 37.628865979381445
    },
    "5": {
      "category": "Deduction",
      "count": 155,
      "percentage": 40.78947368421053
    },
    "16": {
      "category": "Deduction",
      "count": 91,
      "percentage": 51.41242937853108
    },
    "19": {
      "category": "Deduction",
      "count": 65,
      "percentage": 41.66666666666667
    },
    "27": {
      "category": "Deduction",
      "count": 107,
      "percentage": 51.94174757281553
    },
    "11": {
      "category": "Deduction",
      "count": 89,
      "percentage": 45.64102564102564
    },
    "2": {
      "category": "Deduction",
      "count": 336,
      "percentage": 53.674121405750796
    },
    "17": {
      "category": "Deduction",
      "count": 51,
      "percentage": 38.93129770992366
    },
    "8": {
      "category": "Deduction",
      "count": 119,
      "percentage": 53.84615384615385
    },
    "12": {
      "category": "Deduction",
      "count": 81,
      "percentage": 40.298507462686565
    },
    "20": {
      "category": "Deduction",
      "count": 113,
      "percentage": 59.78835978835979
    },
    "22": {
      "category": "Deduction",
      "count": 140,
      "percentage": 46.82274247491639
    },
    "1": {
      "category": "Deduction",
      "count": 89,
      "percentage": 41.013824884792626
    },
    "9": {
      "category": "Deduction",
      "count": 92,
      "percentage": 45.54455445544555
    },
    "25": {
      "category": "Deduction",
      "count": 145,
      "percentage": 71.42857142857143
    },
    "21": {
      "category": "Deduction",
      "count": 55,
      "percentage": 44.354838709677416
    }
  }
}